{
  "StudentName" : "Polat Erduran",
  "StudentId" : {
    "cseCode" : "1501",
    "year" : 2019,
    "order" : 22
  },
  "StudentEmail" : "polaterduran@marun.edu.tr",
  "StudentPhoneNumber" : "05341975215",
  "SemesterNumber" : 7,
  "CompletedCredits" : 71,
  "Gpa" : 1.42,
  "AdvisorName" : "Murat Can Ganiz",
  "Taken Course" : [ {
    "CourseName" : "Atatürk's Prin. & History I",
    "LetterGrade" : "DC",
    "Course" : "ATA121"
  }, {
    "CourseName" : "Introduction to Modern Biology",
    "LetterGrade" : "FF",
    "Course" : "MBG1201"
  }, {
    "CourseName" : "Introduction to Computer Engineering",
    "LetterGrade" : "BA",
    "Course" : "CSE1200"
  }, {
    "CourseName" : "Computer Programming I",
    "LetterGrade" : "AA",
    "Course" : "CSE1241"
  }, {
    "CourseName" : "Calculus I",
    "LetterGrade" : "FF",
    "Course" : "MATH1001"
  }, {
    "CourseName" : "Physics I",
    "LetterGrade" : "BB",
    "Course" : "PHYS1101"
  }, {
    "CourseName" : "Physics Lab I",
    "LetterGrade" : "FF",
    "Course" : "PHYS1103"
  }, {
    "CourseName" : "Turkish Language I",
    "LetterGrade" : "FF",
    "Course" : "TRD121"
  }, {
    "CourseName" : "Atatürk's Prin. & History II",
    "LetterGrade" : "FD",
    "Course" : "ATA122"
  }, {
    "CourseName" : "Computer Programming II",
    "LetterGrade" : "DD",
    "Course" : "CSE1242"
  }, {
    "CourseName" : "Calculus II",
    "LetterGrade" : "FF",
    "Course" : "MATH1002"
  }, {
    "CourseName" : "Linear Algebra",
    "LetterGrade" : "FF",
    "Course" : "MATH2256"
  }, {
    "CourseName" : "Physics II",
    "LetterGrade" : "BB",
    "Course" : "PHYS1102"
  }, {
    "CourseName" : "Physics Lab II",
    "LetterGrade" : "CC",
    "Course" : "PHYS1104"
  }, {
    "CourseName" : "Turkish Language II",
    "LetterGrade" : "BA",
    "Course" : "TRD122"
  }, {
    "CourseName" : "Discrete Comp. Structures",
    "LetterGrade" : "CC",
    "Course" : "CSE2023"
  }, {
    "CourseName" : "Data Structures",
    "LetterGrade" : "FF",
    "Course" : "CSE2225"
  }, {
    "CourseName" : "Engineering Economy",
    "LetterGrade" : "BB",
    "Course" : "ECON2004"
  }, {
    "CourseName" : "Electric Circuits",
    "LetterGrade" : "FD",
    "Course" : "EE2031"
  }, {
    "CourseName" : "Differential Equations",
    "LetterGrade" : "FG",
    "Course" : "MATH2055"
  }, {
    "CourseName" : "System Programming",
    "LetterGrade" : "BB",
    "Course" : "CSE2138"
  }, {
    "CourseName" : "Principles of Programming Languages",
    "LetterGrade" : "DC",
    "Course" : "CSE2260"
  }, {
    "CourseName" : "Prob. and Stat. for Computer Engineering",
    "LetterGrade" : "CC",
    "Course" : "STAT2253"
  }, {
    "CourseName" : "Digital Logic Design",
    "LetterGrade" : "AA",
    "Course" : "CSE3215"
  }, {
    "CourseName" : "Object-Oriented Sofware Design",
    "LetterGrade" : "FG",
    "Course" : "CSE3063"
  }, {
    "CourseName" : "Modeling and Discrete Simulation",
    "LetterGrade" : "BB",
    "Course" : "IE3081"
  }, {
    "CourseName" : "Computer Organization",
    "LetterGrade" : "FF",
    "Course" : "CSE3038"
  }, {
    "CourseName" : "Formal Lang. & Auto. Theory",
    "LetterGrade" : "FF",
    "Course" : "CSE3264"
  }, {
    "CourseName" : "Technical Comm. and Entrepreneurship",
    "LetterGrade" : "DZ",
    "Course" : "COM2202"
  }, {
    "CourseName" : "German for Beginners",
    "LetterGrade" : "DC",
    "Course" : "YDA1001"
  } ],
  "Requested Course" : [ {
    "Course" : "Computer Networks"
  }, {
    "Course" : "Work Safety I"
  }, {
    "Course" : "Introduction to Machine Learning"
  }, {
    "Course" : "Introduction to Modern Biology"
  }, {
    "Course" : "Calculus I"
  }, {
    "Course" : "Physics Lab I"
  }, {
    "Course" : "Turkish Language I"
  }, {
    "Course" : "Data Structures"
  }, {
    "Course" : "Electric Circuits"
  }, {
    "Course" : "Differential Equations"
  }, {
    "Course" : "Object-Oriented Sofware Design"
  }, {
    "Course" : "Introduction to Cryptography"
  } ],
  "Enrolled Course" : [ {
    "Course" : "Computer Networks"
  }, {
    "Course" : "Work Safety I"
  }, {
    "Course" : "Introduction to Machine Learning"
  }, {
    "Course" : "Introduction to Modern Biology"
  }, {
    "Course" : "Calculus I"
  }, {
    "Course" : "Physics Lab I"
  }, {
    "Course" : "Turkish Language I"
  }, {
    "Course" : "Introduction to Cryptography"
  } ],
  "Output" : [ "The system didn't allow CSE4219 because student failed prereq. CSE3038", "The advisor didn't approve graduation project CSE4297 because student completed credits < 100", "The system didn't allow CSE4034 because student failed prereq. CSE3033", "Advisor didn't approve CSE2225 because of two hours collision with MBG1201 in schedule", "Advisor didn't approve EE2031 because of two hours collision with CSE4288 in schedule", "Advisor didn't approve MATH2055 because of two hours collision with MATH1001 in schedule", "Advisor didn't approve CSE3063 because of two hours collision with CSE4288 in schedule" ]
}