{
  "StudentName" : "Dilek Kalelioğlu",
  "StudentId" : {
    "cseCode" : "1501",
    "year" : 2021,
    "order" : 48
  },
  "StudentEmail" : "dilekkalelioglu@marun.edu.tr",
  "StudentPhoneNumber" : "05096367145",
  "SemesterNumber" : 3,
  "CompletedCredits" : 32,
  "Gpa" : 1.53,
  "AdvisorName" : "Çiğdem Eroğlu Erdem",
  "Taken Course" : [ {
    "CourseName" : "Atatürk's Prin. & History I",
    "LetterGrade" : "FD",
    "Course" : "ATA121"
  }, {
    "CourseName" : "Introduction to Modern Biology",
    "LetterGrade" : "FF",
    "Course" : "MBG1201"
  }, {
    "CourseName" : "Introduction to Computer Engineering",
    "LetterGrade" : "AA",
    "Course" : "CSE1200"
  }, {
    "CourseName" : "Computer Programming I",
    "LetterGrade" : "DZ",
    "Course" : "CSE1241"
  }, {
    "CourseName" : "Calculus I",
    "LetterGrade" : "AA",
    "Course" : "MATH1001"
  }, {
    "CourseName" : "Physics I",
    "LetterGrade" : "FF",
    "Course" : "PHYS1101"
  }, {
    "CourseName" : "Physics Lab I",
    "LetterGrade" : "FF",
    "Course" : "PHYS1103"
  }, {
    "CourseName" : "Turkish Language I",
    "LetterGrade" : "FF",
    "Course" : "TRD121"
  }, {
    "CourseName" : "Atatürk's Prin. & History II",
    "LetterGrade" : "DD",
    "Course" : "ATA122"
  }, {
    "CourseName" : "Calculus II",
    "LetterGrade" : "CC",
    "Course" : "MATH1002"
  }, {
    "CourseName" : "Linear Algebra",
    "LetterGrade" : "DD",
    "Course" : "MATH2256"
  }, {
    "CourseName" : "Physics II",
    "LetterGrade" : "DD",
    "Course" : "PHYS1102"
  }, {
    "CourseName" : "Physics Lab II",
    "LetterGrade" : "AA",
    "Course" : "PHYS1104"
  }, {
    "CourseName" : "Turkish Language II",
    "LetterGrade" : "FF",
    "Course" : "TRD122"
  }, {
    "CourseName" : "German for Beginners",
    "LetterGrade" : "AA",
    "Course" : "YDA1001"
  } ],
  "Requested Course" : [ {
    "Course" : "Discrete Comp. Structures"
  }, {
    "Course" : "Engineering Economy"
  }, {
    "Course" : "Electric Circuits"
  }, {
    "Course" : "Differential Equations"
  }, {
    "Course" : "Numerical Methods"
  }, {
    "Course" : "Atatürk's Prin. & History I"
  }, {
    "Course" : "Introduction to Modern Biology"
  }, {
    "Course" : "Computer Programming I"
  }, {
    "Course" : "Physics I"
  }, {
    "Course" : "Physics Lab I"
  }, {
    "Course" : "Turkish Language I"
  } ],
  "Enrolled Course" : [ {
    "Course" : "Discrete Comp. Structures"
  }, {
    "Course" : "Engineering Economy"
  }, {
    "Course" : "Electric Circuits"
  }, {
    "Course" : "Differential Equations"
  }, {
    "Course" : "Numerical Methods"
  }, {
    "Course" : "Introduction to Modern Biology"
  }, {
    "Course" : "Physics I"
  }, {
    "Course" : "Physics Lab I"
  }, {
    "Course" : "Turkish Language I"
  } ],
  "Output" : [ "The system didn't allow CSE2225 because student failed prereq. CSE1242", "Advisor didn't approve ATA121 because of two hours collision with CSE2023 in schedule", "Advisor didn't approve CSE1241 because of two hours collision with EE2031 in schedule" ]
}