{
  "StudentName" : "Ali Saip Saltık",
  "StudentId" : {
    "cseCode" : "1501",
    "year" : 2019,
    "order" : 40
  },
  "StudentEmail" : "alisaipsaltik@marun.edu.tr",
  "StudentPhoneNumber" : "05293534922",
  "SemesterNumber" : 7,
  "CompletedCredits" : 48,
  "Gpa" : 1.08,
  "AdvisorName" : "Mustafa Ağaoğlu",
  "Taken Course" : [ {
    "CourseName" : "Atatürk's Prin. & History I",
    "LetterGrade" : "FF",
    "Course" : "ATA121"
  }, {
    "CourseName" : "Introduction to Modern Biology",
    "LetterGrade" : "CB",
    "Course" : "MBG1201"
  }, {
    "CourseName" : "Introduction to Computer Engineering",
    "LetterGrade" : "FF",
    "Course" : "CSE1200"
  }, {
    "CourseName" : "Computer Programming I",
    "LetterGrade" : "FG",
    "Course" : "CSE1241"
  }, {
    "CourseName" : "Calculus I",
    "LetterGrade" : "FF",
    "Course" : "MATH1001"
  }, {
    "CourseName" : "Physics I",
    "LetterGrade" : "DZ",
    "Course" : "PHYS1101"
  }, {
    "CourseName" : "Physics Lab I",
    "LetterGrade" : "FF",
    "Course" : "PHYS1103"
  }, {
    "CourseName" : "Turkish Language I",
    "LetterGrade" : "DD",
    "Course" : "TRD121"
  }, {
    "CourseName" : "Atatürk's Prin. & History II",
    "LetterGrade" : "DZ",
    "Course" : "ATA122"
  }, {
    "CourseName" : "Calculus II",
    "LetterGrade" : "BB",
    "Course" : "MATH1002"
  }, {
    "CourseName" : "Linear Algebra",
    "LetterGrade" : "FF",
    "Course" : "MATH2256"
  }, {
    "CourseName" : "Physics II",
    "LetterGrade" : "BB",
    "Course" : "PHYS1102"
  }, {
    "CourseName" : "Physics Lab II",
    "LetterGrade" : "CC",
    "Course" : "PHYS1104"
  }, {
    "CourseName" : "Turkish Language II",
    "LetterGrade" : "BB",
    "Course" : "TRD122"
  }, {
    "CourseName" : "Discrete Comp. Structures",
    "LetterGrade" : "CC",
    "Course" : "CSE2023"
  }, {
    "CourseName" : "Engineering Economy",
    "LetterGrade" : "FF",
    "Course" : "ECON2004"
  }, {
    "CourseName" : "Electric Circuits",
    "LetterGrade" : "BA",
    "Course" : "EE2031"
  }, {
    "CourseName" : "Differential Equations",
    "LetterGrade" : "FF",
    "Course" : "MATH2055"
  }, {
    "CourseName" : "System Programming",
    "LetterGrade" : "FG",
    "Course" : "CSE2138"
  }, {
    "CourseName" : "Electronics",
    "LetterGrade" : "DD",
    "Course" : "EE2032"
  }, {
    "CourseName" : "Prob. and Stat. for Computer Engineering",
    "LetterGrade" : "DC",
    "Course" : "STAT2253"
  }, {
    "CourseName" : "Digital Logic Design",
    "LetterGrade" : "BB",
    "Course" : "CSE3215"
  }, {
    "CourseName" : "Modeling and Discrete Simulation",
    "LetterGrade" : "FD",
    "Course" : "IE3081"
  }, {
    "CourseName" : "Formal Lang. & Auto. Theory",
    "LetterGrade" : "FF",
    "Course" : "CSE3264"
  }, {
    "CourseName" : "Technical Comm. and Entrepreneurship",
    "LetterGrade" : "DZ",
    "Course" : "COM2202"
  }, {
    "CourseName" : "Strategic Entrepreneurship",
    "LetterGrade" : "DZ",
    "Course" : "BUS1004"
  } ],
  "Requested Course" : [ {
    "Course" : "Computer Networks"
  }, {
    "Course" : "Work Safety I"
  }, {
    "Course" : "Introduction to Machine Learning"
  }, {
    "Course" : "Atatürk's Prin. & History I"
  }, {
    "Course" : "Introduction to Computer Engineering"
  }, {
    "Course" : "Computer Programming I"
  }, {
    "Course" : "Calculus I"
  }, {
    "Course" : "Physics I"
  }, {
    "Course" : "Physics Lab I"
  }, {
    "Course" : "Engineering Economy"
  }, {
    "Course" : "Differential Equations"
  }, {
    "Course" : "Modeling and Discrete Simulation"
  }, {
    "Course" : "Strategic Entrepreneurship"
  } ],
  "Enrolled Course" : [ {
    "Course" : "Computer Networks"
  }, {
    "Course" : "Work Safety I"
  }, {
    "Course" : "Introduction to Machine Learning"
  }, {
    "Course" : "Calculus I"
  }, {
    "Course" : "Physics I"
  }, {
    "Course" : "Physics Lab I"
  }, {
    "Course" : "Strategic Entrepreneurship"
  } ],
  "Output" : [ "The system didn't allow CSE4219 because student failed prereq. CSE3038", "The advisor didn't approve graduation project CSE4297 because student completed credits < 100", "The advisor didn't approve TECSE4067 because student completed credits < 70", "The system didn't allow CSE4217 because student failed prereq. CSE3038", "Advisor didn't approve ATA121 because of two hours collision with CSE4074 in schedule", "Advisor didn't approve CSE1200 because of two hours collision with ISG121 in schedule", "Advisor didn't approve CSE1241 because of two hours collision with CSE4288 in schedule", "Advisor didn't approve ECON2004 because of two hours collision with ISG121 in schedule", "Advisor didn't approve MATH2055 because of two hours collision with MATH1001 in schedule", "Advisor didn't approve IE3081 because of two hours collision with MATH1001 in schedule" ]
}